pystatuspage
