Metadata-Version: 1.0
Name: pystatuspage
Version: 0.0.2
Summary: pystatuspage is a simple api wrapper for statuspage api
Home-page: https://github.com/srgrn/pystatuspage
Author: Eran Zimbler
Author-email: eran@zimbler.net
License: UNKNOWN
Keywords: api_wrapper,statuspage,statuspage.io
Platform: UNKNOWN
